setup.cfg
setup.py
bin/get_vpc_logs
getawslogs/__init__.py
getawslogs/cloud_watch_logs.py
getawslogs/get_logs.py
getawslogs/sumo_client.py
getawslogs.egg-info/PKG-INFO
getawslogs.egg-info/SOURCES.txt
getawslogs.egg-info/dependency_links.txt
getawslogs.egg-info/requires.txt
getawslogs.egg-info/top_level.txt