Metadata-Version: 1.0
Name: getawslogs
Version: 0.1.0
Summary: Python package and non-interactive commandline program(s) to get AWS logs.
Home-page: https://github.com/MelchiSalins/getawslogs
Author: Melchi Salins
Author-email: melchisalins@icloud.com
License: UNKNOWN
Keywords: DevOps AWS Logs
Platform: UNKNOWN
